baseclasses/__init__.py
baseclasses/core.py
baseclasses/py.typed
baseclasses/version.py
baseclasses/tests/__init__.py
baseclasses/tests/test_compare.py
baseclasses/tests/test_core.py
baseclasses-0.1.1.dist-info/LICENSE
baseclasses-0.1.1.dist-info/METADATA
baseclasses-0.1.1.dist-info/WHEEL
baseclasses-0.1.1.dist-info/top_level.txt
baseclasses-0.1.1.dist-info/RECORD
