Metadata-Version: 2.1
Name: baseclasses
Version: 0.1.1
Summary: Dataclasses alternative
Home-page: https://github.com/yanovs/baseclasses
License: Apache License 2.0
Project-URL: Packaging, https://pypi.org/project/baseclasses/
Project-URL: Source, https://github.com/yanovs/baseclasses
Project-URL: Tracker, https://github.com/yanovs/baseclasses/issues
Keywords: dataclasses
Platform: any
Classifier: Development Status :: 4 - Beta
Classifier: Intended Audience :: Developers
Classifier: Operating System :: OS Independent
Classifier: Programming Language :: Python :: 3.7
Classifier: Programming Language :: Python :: 3.8
Classifier: Programming Language :: Python :: 3.9
Classifier: Programming Language :: Python :: 3.10
Classifier: Programming Language :: Python :: 3.11
Classifier: Programming Language :: Python :: Implementation :: CPython
Classifier: Programming Language :: Python :: Implementation :: PyPy
Classifier: Topic :: Software Development :: Libraries
Classifier: Topic :: Utilities
Requires-Python: >=3.7
License-File: LICENSE
Provides-Extra: building
Requires-Dist: build (>=0.6.0) ; extra == 'building'
Requires-Dist: setuptools-scm[toml] (>=3.4) ; extra == 'building'
Requires-Dist: wheel (>=0.38.0) ; extra == 'building'
Provides-Extra: testing
Requires-Dist: black (>=22.8) ; extra == 'testing'
Requires-Dist: cached-property (>=1.5.2) ; extra == 'testing'
Requires-Dist: docformatter (>=1.5.0) ; extra == 'testing'
Requires-Dist: flake8 (>=5.0.4) ; extra == 'testing'
Requires-Dist: isort (>=5.2.2) ; extra == 'testing'
Requires-Dist: mypy (>=0.800) ; extra == 'testing'
Requires-Dist: pytest (>=6.2.5) ; extra == 'testing'
Requires-Dist: pytest-cov (<3,>=2) ; extra == 'testing'
Requires-Dist: pyright (>=0.0.13) ; extra == 'testing'
Requires-Dist: tox (>=3.27.1) ; extra == 'testing'
